myapp_plugin_calculator/__init__.py
myapp_plugin_calculator/interactive_myapp.py
myapp_plugin_calculator/plugin.py
myapp_plugin_calculator-0.4.4.dist-info/licenses/LICENSE
myapp_plugin_calculator-0.4.4.dist-info/METADATA
myapp_plugin_calculator-0.4.4.dist-info/WHEEL
myapp_plugin_calculator-0.4.4.dist-info/entry_points.txt
myapp_plugin_calculator-0.4.4.dist-info/top_level.txt
myapp_plugin_calculator-0.4.4.dist-info/RECORD
