Metadata-Version: 2.4
Name: myapp-plugin-calculator
Version: 0.4.4
Summary: MyApp的高级科学计算器插件 - 反向更新
Author-email: Sans <2890517374@qq.com>
Project-URL: Homepage, https://github.com/yourusername/myapp-plugin-calculator
Requires-Python: >=3.7
License-File: LICENSE
Requires-Dist: my-app-core
Dynamic: license-file
